tangazify/__init__.py
tangazify/api.py
tangazify/config.py
tangazify/display.py
tangazify/utils.py
tests/__init__.py
tests/test_api.py
tests/test_display.py
tangazify_client-0.1.dist-info/METADATA
tangazify_client-0.1.dist-info/WHEEL
tangazify_client-0.1.dist-info/top_level.txt
tangazify_client-0.1.dist-info/RECORD
