Metadata-Version: 2.1
Name: tangazify-client
Version: 0.1
Requires-Dist: requests
Requires-Dist: numpy
Requires-Dist: opencv-python
